.DS_Store
sparce/__init__.py
sparce/args_parse.py
sparce/bin_manipulations.py
sparce/feature_selection.py
sparce/parseVariantAnnotationFile.py
sparce/parse_gene_annotation.py
sparce/preprocessTranscriptomics.py
sparce/sparce.py
sparce-0.1.14.dist-info/LICENSE
sparce-0.1.14.dist-info/METADATA
sparce-0.1.14.dist-info/WHEEL
sparce-0.1.14.dist-info/top_level.txt
sparce-0.1.14.dist-info/RECORD
