Metadata-Version: 2.1
Name: sparce
Version: 0.1.14
Summary: A python package for automated feature selection
Home-page: https://github.com/michaelSkaro/sparce/
Author: Michael Skaro
Author-email: mskaro.ms@gmail.com
Project-URL: Bug Tracker, https://github.com/michaelSkaro/sparce/issues
Classifier: Programming Language :: Python :: 3
Classifier: License :: OSI Approved :: MIT License
Classifier: Operating System :: OS Independent
Requires-Python: >=3.6
License-File: LICENSE
Requires-Dist: seaborn
Requires-Dist: matplotlib
Requires-Dist: numpy
Requires-Dist: pandas
Requires-Dist: scikit-learn
